kaist_or_gym/__init__.py
kaist_or_gym/registration.py
kaist_or_gym/version.py
kaist_or_gym/envs/__init__.py
kaist_or_gym/envs/traffic_control_env.py
kaist_or_gym/envs/windy_gridworld.py
kaist_or_gym-0.1.10.dist-info/METADATA
kaist_or_gym-0.1.10.dist-info/WHEEL
kaist_or_gym-0.1.10.dist-info/top_level.txt
kaist_or_gym-0.1.10.dist-info/RECORD
