Metadata-Version: 2.4
Name: kaist-or-gym
Version: 0.1.10
Summary: Custom Gym/Gymnasium environments for operations research problems
Author-email: Kihyuk Hong <kihyukh@kaist.ac.kr>
License-Expression: MIT
Requires-Python: >=3.9
Requires-Dist: gymnasium>=1.2.0
Requires-Dist: numpy>=1.23
Requires-Dist: matplotlib>=3.0
Requires-Dist: ipython==7.34.0
Provides-Extra: dev
Requires-Dist: pytest>=7; extra == "dev"
Requires-Dist: ruff; extra == "dev"
Requires-Dist: mypy; extra == "dev"
Provides-Extra: examples
Provides-Extra: test
Requires-Dist: pytest>=7; extra == "test"
Requires-Dist: gymnasium[other]>=0.29; extra == "test"
